tutors3scorm/__about__.py
tutors3scorm/__init__.py
tutors3scorm/plugin.py
tutors3scorm/patches/.gitignore
tutors3scorm/patches/caddyfile-cms
tutors3scorm/patches/caddyfile-lms
tutors3scorm/patches/openedx-cms-common-settings
tutors3scorm/patches/openedx-lms-common-settings
tutor_contrib_s3scorm-19.0.0.dist-info/METADATA
tutor_contrib_s3scorm-19.0.0.dist-info/WHEEL
tutor_contrib_s3scorm-19.0.0.dist-info/entry_points.txt
tutor_contrib_s3scorm-19.0.0.dist-info/top_level.txt
tutor_contrib_s3scorm-19.0.0.dist-info/RECORD
