Metadata-Version: 2.1
Name: tutor-contrib-s3scorm
Version: 19.0.0
Summary: s3scorm plugin for Tutor
Home-page: https://github.com/aulasneo/tutor-contrib-s3scorm
Author: Andrés González
License: AGPLv3
Project-URL: Code, https://github.com/aulasneo/tutor-contrib-s3scorm
Project-URL: Issue tracker, https://github.com/aulasneo/tutor-contrib-s3scorm/issues
Classifier: Development Status :: 3 - Alpha
Classifier: Intended Audience :: Developers
Classifier: License :: OSI Approved :: GNU Affero General Public License v3
Classifier: Operating System :: OS Independent
Classifier: Programming Language :: Python
Classifier: Programming Language :: Python :: 3.7
Classifier: Programming Language :: Python :: 3.8
Classifier: Programming Language :: Python :: 3.9
Classifier: Programming Language :: Python :: 3.10
Requires-Python: >=3.7
Requires-Dist: tutor<20.0.0,>=19.0.0
